<?xml version="1.0" encoding="utf-8"?>
<!DOCTYPE hibernate-mapping PUBLIC "-//Hibernate/Hibernate Mapping DTD 3.0//EN"
"http://hibernate.sourceforge.net/hibernate-mapping-3.0.dtd">
<!-- 
    Mapping file autogenerated by MyEclipse Persistence Tools
-->
<hibernate-mapping>
    <class name="dao.Basicinfo" table="basicinfo" catalog="douban">
        <id name="id" type="java.lang.Integer">
            <column name="Id" />
            <generator class="native" />
        </id>
        <property name="nickName" type="java.lang.String">
            <column name="nickName" not-null="true">
                <comment>用户名称</comment>
            </column>
        </property>
        <property name="userName" type="java.lang.String">
            <column name="userName" not-null="true">
                <comment>类似于用户Id，在系统中是唯一的，但是不一定是数字。</comment>
            </column>
        </property>
        <property name="address" type="java.lang.String">
            <column name="address" />
        </property>
        <property name="friendsTag" type="java.lang.Integer">
            <column name="friendsTag">
                <comment>该tag表示是否已经对用户关注人数完成了抓取</comment>
            </column>
        </property>
        <property name="friendsNum" type="java.lang.Integer">
            <column name="friendsNum">
                <comment>该用户关注的用户数目</comment>
            </column>
        </property>
        <property name="revLinkTag" type="java.lang.Integer">
            <column name="revLinkTag">
                <comment>表示是否对该用户的被关注情况进行了抓取</comment>
            </column>
        </property>
        <property name="revLinkNum" type="java.lang.Integer">
            <column name="revLinkNum">
                <comment>关注该用户的人数</comment>
            </column>
        </property>
        <property name="groupTag" type="java.lang.Integer">
            <column name="groupTag">
                <comment>表示是否对用户加入小组的情况进行了抓取</comment>
            </column>
        </property>
        <property name="groupNum" type="java.lang.Integer">
            <column name="groupNum">
                <comment>加入小组的数目</comment>
            </column>
        </property>
        <property name="douListTag" type="java.lang.Integer">
            <column name="douListTag" />
        </property>
        <property name="douListNum" type="java.lang.Integer">
            <column name="douListNum">
                <comment>加入豆列的数目</comment>
            </column>
        </property>
        <property name="douTag" type="java.lang.Integer">
            <column name="douTag">
                <comment>标志是否对同城活动进行了抓取</comment>
            </column>
        </property>
        <property name="eventNum" type="java.lang.Integer">
            <column name="eventNum">
                <comment>同城活动的数目</comment>
            </column>
        </property>
        <property name="likeTag" type="java.lang.Integer">
            <column name="likeTag">
                <comment>标志是否对喜欢情况进行了抓取</comment>
            </column>
        </property>
        <property name="notesTag" type="java.lang.Integer">
            <column name="notesTag">
                <comment>标志是否对用户日记情况进行抓取</comment>
            </column>
        </property>
        <property name="statusTag" type="java.lang.Integer">
            <column name="statusTag">
                <comment>标志是否对用户广播情况进行抓取</comment>
            </column>
        </property>
        <property name="movieTag" type="java.lang.Integer">
            <column name="movieTag" />
        </property>
        <property name="bookTag" type="java.lang.Integer">
            <column name="bookTag" />
        </property>
        <property name="musicTag" type="java.lang.Integer">
            <column name="musicTag" />
        </property>
        <property name="minsiteTag" type="java.lang.Integer">
            <column name="minsiteTag">
                <comment>对关注的小站情况进行抓取</comment>
            </column>
        </property>
        <property name="remark" type="java.lang.String">
            <column name="remark" />
        </property>
    </class>
</hibernate-mapping>
